<?xml version="1.0" encoding="UTF-8"?>
<!DOCTYPE mapper PUBLIC "-//mybatis.org//DTD Mapper 3.0//EN"
        "http://mybatis.org/dtd/mybatis-3-mapper.dtd">

<mapper namespace="com.spring.home.mapper.InteriorMapper">

    <!-- 데이터 베이스 테스트 -->
    
<insert id="insertInteriorData" parameterType="com.spring.home.dto.InteriorDTO">
	insert into INTERIOR (c_id,c_kind,c_name,i_tag,i_text) values 
	(#{c_id},#{c_kind},#{c_name},#{i_tag},#{i_text})	
</insert>

<insert id="insertInteriorExampleData" parameterType="com.spring.home.dto.InteriorExampleDTO">
	insert into I_EXAMPLE (c_id,c_kind,c_name,ie_tag,ie_tag2,ie_content) values 
	(#{c_id},#{c_kind},#{c_name},#{ie_tag},#{ie_tag2},#{ie_content})	
</insert>

<insert id="insertBookingData" parameterType="com.spring.home.dto.BookingDTO">
	insert into Booking (id, c_id,c_kind,c_name,b_kind,b_long,b_date,b_status,b_content,b_answer) values 
	(#{id}, #{c_id},#{c_kind},#{c_name},#{b_kind},#{b_long},#{b_date},#{b_status},#{b_content},#{b_answer})	
</insert>

<insert id="insertInvoiceData" parameterType="com.spring.home.dto.InvoiceDTO">
	insert into INVOICE (id, c_id,c_kind,c_name,b_createdDate,invoice_no,invoice_kind) values 
	(#{id}, #{c_id},#{c_kind},#{c_name},#{b_createdDate},#{invoice_no},#{invoice_kind})	
</insert>

<insert id="insertInvoiceDetails" parameterType="com.spring.home.dto.InvoiceDTO">
    INSERT ALL
    <foreach collection="details" item="item" index="idx">
        INTO INVOICE_DETAIL (id, c_id,c_kind,c_name,b_createdDate,invoice_no,invoice_kind,INVOICE_TEXT,INVOICE_PRICE)
        VALUES (#{id}, #{c_id},#{c_kind},#{c_name},#{b_createdDate},#{invoice_no},#{invoice_kind},#{item.invoice_text}, #{item.invoice_price})
    </foreach>  
    SELECT * FROM DUAL  
</insert>

<insert id="insertInvoiceDetailData" parameterType="com.spring.home.dto.InvoiceDetailDTO">
    INSERT INTO INVOICE_DETAIL (id, c_id,c_kind,c_name,b_createdDate,invoice_no,INVOICE_TEXT,INVOICE_PRICE)
        VALUES (#{id}, #{c_id},#{c_kind},#{c_name},#{b_createdDate},#{invoice_no},#{invoice_text}, #{invoice_price})
</insert>

<select id="getLists" resultType="com.spring.home.dto.CompanyDTO">
	select c_id,c_kind,c_name,c_tel,c_addr,c_info,c_boss from COMPANY WHERE c_kind like 'interior'
</select>

<select id="getArticleLists" resultType="com.spring.home.dto.InteriorDTO">
	select c_id,c_kind,c_name,i_tag,i_text from INTERIOR
</select>

<select id="getReadData"  parameterType="hashMap" resultType="com.spring.home.dto.InteriorDTO">
	select c_id,c_kind,c_name,i_tag,i_text
	from INTERIOR where c_id like '%' || #{c_id} || '%'
      and c_kind like '%' || #{c_kind} || '%'
      and c_name like '%' || #{c_name} || '%' 
</select>

<select id="getExamples"  parameterType="hashMap" resultType="com.spring.home.dto.InteriorExampleDTO">
	select c_id,c_kind,c_name,ie_content,ie_tag,ie_tag2
	from I_EXAMPLE where c_id like '%' || #{c_id} || '%'
      and c_kind like '%' || #{c_kind} || '%'
      and c_name like '%' || #{c_name} || '%' 
</select>

<select id="getBookings"  parameterType="hashMap" resultType="com.spring.home.dto.BookingDTO">
	select id,b_createddate,c_id,c_kind,c_name,b_kind,b_date,b_status,b_content,b_answer
	from Booking where c_id like '%' || #{c_id} || '%'
      and c_kind like '%' || #{c_kind} || '%'
      and c_name like '%' || #{c_name} || '%' 
</select>

<select id="getInvoices"  parameterType="hashMap" resultType="com.spring.home.dto.InvoiceDTO">
	select id,b_createddate,c_id,c_kind,c_name,invoice_no,invoice_kind
	from INVOICE where id like '%' || #{id} || '%'
		and c_id like '%' || #{c_id} || '%'
      and c_kind like '%' || #{c_kind} || '%'
      and c_name like '%' || #{c_name} || '%' 
      and b_createdDate = #{b_createdDate, jdbcType=TIMESTAMP}
</select>

<select id="getInvoicedetails"  parameterType="hashMap" resultType="com.spring.home.dto.InvoiceDetailDTO">
	select id,b_createddate,c_id,c_kind,c_name,invoice_no,invoice_kind,invoice_text,invoice_price
	from INVOICE_DETAIL where id like '%' || #{id} || '%'
		and c_id like '%' || #{c_id} || '%'
      and c_kind like '%' || #{c_kind} || '%'
      and c_name like '%' || #{c_name} || '%' 
      and b_createdDate = #{b_createdDate, jdbcType=TIMESTAMP}
      and invoice_no like '%' || #{invoice_no} || '%'
      and invoice_kind like '%' || #{invoice_kind} || '%' 
</select>


</mapper>